argspect/__init__.py
benchmarks/__init__.py
docs/__init__.py
docs/source/__init__.py
docs/source/conf.py
tests/__init__.py
tests/test_imports.py
tests/test_sanity.py
Argspect-0.0.1.dist-info/LICENSE.md
Argspect-0.0.1.dist-info/METADATA
Argspect-0.0.1.dist-info/WHEEL
Argspect-0.0.1.dist-info/entry_points.txt
Argspect-0.0.1.dist-info/top_level.txt
Argspect-0.0.1.dist-info/RECORD
